upms/__init__.py
upms-0.1.dist-info/METADATA
upms-0.1.dist-info/WHEEL
upms-0.1.dist-info/top_level.txt
upms-0.1.dist-info/RECORD
